smyoon_sense_api/__init__.py
smyoon_sense_api/api_client.py
smyoon_sense_api/configuration.py
smyoon_sense_api/exceptions.py
smyoon_sense_api/model_utils.py
smyoon_sense_api/rest.py
smyoon_sense_api/api/__init__.py
smyoon_sense_api/api/audio_session_api.py
smyoon_sense_api/apis/__init__.py
smyoon_sense_api/model/__init__.py
smyoon_sense_api/model/audio_chunk.py
smyoon_sense_api/model/audio_metadatas.py
smyoon_sense_api/model/audio_type.py
smyoon_sense_api/model/create_session.py
smyoon_sense_api/model/default_sensitivity.py
smyoon_sense_api/model/generic_error.py
smyoon_sense_api/model/page.py
smyoon_sense_api/model/predict_request.py
smyoon_sense_api/model/predict_response.py
smyoon_sense_api/model/sense.py
smyoon_sense_api/model/sense_event.py
smyoon_sense_api/model/sense_event_tag.py
smyoon_sense_api/model/session_refs.py
smyoon_sense_api/model/session_result.py
smyoon_sense_api/model/session_status.py
smyoon_sense_api/model/tags_sensitivity.py
smyoon_sense_api/model/update_session.py
smyoon_sense_api/model/window_hop.py
smyoon_sense_api/models/__init__.py
smyoon_sense_api-1.6.100.dist-info/METADATA
smyoon_sense_api-1.6.100.dist-info/WHEEL
smyoon_sense_api-1.6.100.dist-info/RECORD
