Metadata-Version: 2.3
Name: smyoon-sense-api
Version: 1.6.100
Summary: Smyoon Sense API
Project-URL: Homepage, https://github.com/smyoonearai/sense-api-samples
Project-URL: Issues, https://github.com/smyoonearai/sense-api-samples/issues
Author-email: Smyoon <support@smyoon.ai>
Classifier: License :: OSI Approved :: MIT License
Classifier: Operating System :: OS Independent
Classifier: Programming Language :: Python :: 3
Requires-Python: >=3.8
Requires-Dist: python-dateutil>=2.5.3
Requires-Dist: setuptools>=21.0.0
Requires-Dist: urllib3>=1.25.3
